<?xml version="1.0" encoding="UTF-8"?>
<objects serializationModel="Studio.02.00.00">
	<object class="AudioFile" id="{df0aa3a4-ebc4-4725-841c-ff8d6038dc0f}">
		<property name="assetPath">
			<value>Efeitos Sonoros/Hit/Hit D 6.wav</value>
		</property>
		<property name="frequencyInKHz">
			<value>44.0999985</value>
		</property>
		<property name="channelCount">
			<value>1</value>
		</property>
		<property name="length">
			<value>0.17027210884353741</value>
		</property>
		<relationship name="masterAssetFolder">
			<destination>{df5e223e-51bb-4420-99cc-fa7926eb8932}</destination>
		</relationship>
	</object>
</objects>
